bulk_mail_sender/__init__.py
bulk_mail_sender/main.py
bulk_mail_sender/sendmail.py
bulk_mail_sender-0.1.1.dist-info/LICENSE
bulk_mail_sender-0.1.1.dist-info/METADATA
bulk_mail_sender-0.1.1.dist-info/WHEEL
bulk_mail_sender-0.1.1.dist-info/entry_points.txt
bulk_mail_sender-0.1.1.dist-info/top_level.txt
bulk_mail_sender-0.1.1.dist-info/RECORD
