Metadata-Version: 2.1
Name: bulk-mail-sender
Version: 0.1.1
Summary: Send emails in bulk with a CSV listing and a email template.
Home-page: https://github.com/moverest/bulk-mail-sender
Author: Clément Martinez
Author-email: clementmartinezdev@gmail.com
License: UNKNOWN
Platform: UNKNOWN
Requires-Dist: click
Requires-Dist: mako
